CHANGES.txt
LICENSE.txt
MANIFEST.in
README.md
pyproject.toml
setup.cfg
setup.py
tox.ini
src/pyramid_session_multi/__init__.py
src/pyramid_session_multi/py.typed
src/pyramid_session_multi.egg-info/PKG-INFO
src/pyramid_session_multi.egg-info/SOURCES.txt
src/pyramid_session_multi.egg-info/dependency_links.txt
src/pyramid_session_multi.egg-info/not-zip-safe
src/pyramid_session_multi.egg-info/requires.txt
src/pyramid_session_multi.egg-info/top_level.txt
src/pyramid_session_multi/debugtoolbar/__init__.py
src/pyramid_session_multi/debugtoolbar/panels/__init__.py
src/pyramid_session_multi/debugtoolbar/panels/session_multi.py
src/pyramid_session_multi/debugtoolbar/panels/templates/session_multi.dbtmako
tests/__init__.py
tests/_serializers.py
tests/_utils.py
tests/bench_serializers.py
tests/test_config.py
tests/test_debugtoolbar_panel.py
tests/test_session_multi.py