Metadata-Version: 2.4
Name: pyramid_session_multi
Version: 0.4.0
Summary: Provides a framwork for creating multiple adhoc session binds in Pyramid.
Home-page: https://github.com/jvanasco/pyramid_session_multi
Author: Jonathan Vanasco
Author-email: jonathan@findmeon.com
License: MIT
Keywords: pyramid session web
Classifier: Intended Audience :: Developers
Classifier: Framework :: Pyramid
Classifier: Programming Language :: Python
Classifier: Programming Language :: Python :: 3
License-File: LICENSE.txt
Requires-Dist: pyramid>=2
Requires-Dist: typing_extensions
Requires-Dist: zope.interface
Provides-Extra: testing
Requires-Dist: pytest; extra == "testing"
Requires-Dist: pyramid_debugtoolbar>=4.0; extra == "testing"
Dynamic: author
Dynamic: author-email
Dynamic: classifier
Dynamic: description
Dynamic: description-content-type
Dynamic: home-page
Dynamic: keywords
Dynamic: license
Dynamic: license-file
Dynamic: provides-extra
Dynamic: requires-dist
Dynamic: summary
